flask_url_patterns/__init__.py
flask_url_patterns/extension.py
flask_url_patterns/py.typed
flask_url_patterns/typing.py
flask_url_patterns-0.1.3.dist-info/METADATA
flask_url_patterns-0.1.3.dist-info/WHEEL
flask_url_patterns-0.1.3.dist-info/RECORD
