Metadata-Version: 2.1
Name: Flask-Url-Patterns
Version: 0.1.3
Summary: A simple Flask extension to manage URL patterns. In a Django kind of way.
Author: Quentin Boudinel
Author-email: quentin.boudinel@atelier-26.net
Requires-Python: >=3.11,<4.0
Classifier: Programming Language :: Python :: 3
Classifier: Programming Language :: Python :: 3.11
Classifier: Programming Language :: Python :: 3.12
